aec-0.1.3.data/scripts/aec
parsexml/__init__.py
parseyml/__init__.py
aec-0.1.3.dist-info/LICENSE
aec-0.1.3.dist-info/METADATA
aec-0.1.3.dist-info/WHEEL
aec-0.1.3.dist-info/top_level.txt
aec-0.1.3.dist-info/RECORD
