Metadata-Version: 2.1
Name: aec
Version: 0.1.3
Summary: ActiveMQ Easy Config
Home-page: https://github.com/byjg/activemq-easy-config
Author: Joao Gilberto Magalhaes
Author-email: joao@byjg.com.br
License: UNKNOWN
Platform: UNKNOWN
Classifier: Programming Language :: Python :: 3
Classifier: License :: OSI Approved :: MIT License
Classifier: Operating System :: OS Independent
Requires-Dist: pyyaml (>=5.1)
